AddressablesTools/__init__.py
AddressablesTools/classes.py
AddressablesTools/constants.py
AddressablesTools/parser.py
AddressablesTools/Binary/ContentCatalogDataBinaryHeader.py
AddressablesTools/Binary/__init__.py
AddressablesTools/Catalog/ClassJsonObject.py
AddressablesTools/Catalog/ContentCatalogData.py
AddressablesTools/Catalog/ObjectInitializationData.py
AddressablesTools/Catalog/ResourceLocation.py
AddressablesTools/Catalog/SerializedObjectDecoder.py
AddressablesTools/Catalog/SerializedType.py
AddressablesTools/Catalog/WrappedSerializedObject.py
AddressablesTools/Catalog/__init__.py
AddressablesTools/Classes/AssetBundleRequestOptions.py
AddressablesTools/Classes/Hash128.py
AddressablesTools/Classes/TypeReference.py
AddressablesTools/Classes/__init__.py
AddressablesTools/JSON/ContentCatalogDataJson.py
AddressablesTools/JSON/ObjectInitializationDataJson.py
AddressablesTools/JSON/SerializedTypeJson.py
AddressablesTools/JSON/__init__.py
AddressablesTools/Reader/BinaryReader.py
AddressablesTools/Reader/CatalogBinaryReader.py
AddressablesTools/Reader/__init__.py
addressablestools-0.1.7.dist-info/licenses/LICENSE
addressablestools-0.1.7.dist-info/METADATA
addressablestools-0.1.7.dist-info/WHEEL
addressablestools-0.1.7.dist-info/top_level.txt
addressablestools-0.1.7.dist-info/RECORD
