Metadata-Version: 2.4
Name: addressablestools
Version: 0.1.7
Summary: Python copy of AddressablesTools
Author-email: Jitsu <jitsu233@gmail.com>
License: Copyright (c) 2018 The Python Packaging Authority
Project-URL: Homepage, https://github.com/anosu/AddressablesToolsPy
Project-URL: Bug Reports, https://github.com/anosu/AddressablesToolsPy/issues
Project-URL: Funding, https://donate.pypi.org
Project-URL: Source, https://github.com/anosu/AddressablesToolsPy
Requires-Python: >=3.12
License-File: LICENSE
Requires-Dist: orjson>=3.10.18
Dynamic: license-file
